models_logging/__init__.py
models_logging/admin.py
models_logging/apps.py
models_logging/middleware.py
models_logging/models.py
models_logging/settings.py
models_logging/setup.py
models_logging/signals.py
models_logging/utils.py
models_logging/migrations/__init__.py
models_logging/templates/models_logging/change_form.html
models_logging/templates/models_logging/object_history.html
models_logging/templates/models_logging/revert_changes_confirmation.html
models_logging/templates/models_logging/revert_revision_confirmation.html
Cheetay_logs-1.0.6.dist-info/METADATA
Cheetay_logs-1.0.6.dist-info/WHEEL
Cheetay_logs-1.0.6.dist-info/top_level.txt
Cheetay_logs-1.0.6.dist-info/RECORD
