Metadata-Version: 2.1
Name: Cheetay-logs
Version: 1.0.6
Summary: Add logging of models from save, delete signals
Home-page: https://github.com/BugInoculum/Cheetay_logs
Author: Ibrahim
Author-email: muhammad.ibrahim@cheetay.pk
License: MIT
Keywords: Cheetay logging
Platform: UNKNOWN
Classifier: Development Status :: 5 - Production/Stable
Classifier: Environment :: Web Environment
Classifier: Framework :: Django
Classifier: Framework :: Django :: 1.8
Classifier: Framework :: Django :: 1.9
Classifier: Framework :: Django :: 1.10
Classifier: Framework :: Django :: 1.11
Classifier: Framework :: Django :: 2.0
Classifier: Framework :: Django :: 3.0
Classifier: Intended Audience :: Developers
Classifier: License :: OSI Approved :: MIT License
Classifier: Operating System :: OS Independent
Classifier: Programming Language :: Python
Classifier: Programming Language :: Python :: 3
Classifier: Topic :: Internet :: WWW/HTTP
Classifier: Topic :: Software Development :: Libraries :: Python Modules
Requires-Dist: django (==1.11.15)
Requires-Dist: python-dateutil
Requires-Dist: djongo (==1.2.23)
Requires-Dist: pymongo (==3.8.0)
